[
  {
    "topic": "Grammys",
    "score": 9.5,
    "source": "twitter",
    "discovered_at": "2026-02-02T11:22:59.969244+00:00",
    "region": "twitter_us",
    "niche": "General",
    "tweets": [
      {
        "text": "“Nobody is illegal on stolen land. We need to keep fighting and speaking up. Our voices do matter.\"\n\n— Billie Eilish during her acceptance speech at the #GRAMMYs https://t.co/SpVwvUu3GD",
        "likes": 188042,
        "retweets": 29253,
        "replies": 1332,
        "timestamp": "Mon Feb 02 03:16:32 +0000 2026",
        "author": "PopCrave"
      },
      {
        "text": "It’s 1:00 am and Donald Trump is awake furiously posting on social media about the Grammys. He says he’s suing Trevor Noah for joking about him being on Epstein island. What a snowflake!!! So much for free speech! https://t.co/dy6qLHAHuf",
        "likes": 7661,
        "retweets": 1090,
        "replies": 795,
        "timestamp": "Mon Feb 02 06:15:20 +0000 2026",
        "author": "harryjsisson"
      },
      {
        "text": "For the first time in GRAMMYs    history, Bruno has lost all his nominations thanks to Rose. Congrats, girl, you actually achieved the impossible. https://t.co/cI30efZOC6",
        "likes": 25921,
        "retweets": 3987,
        "replies": 292,
        "timestamp": "Mon Feb 02 04:19:31 +0000 2026",
        "author": "ThePopBase"
      },
      {
        "text": "Bad Bunny makes history with the first Spanish-language album to win Album of the Year at the #GRAMMYs. https://t.co/Lzn6gEA9XH",
        "likes": 83515,
        "retweets": 13026,
        "replies": 260,
        "timestamp": "Mon Feb 02 04:50:10 +0000 2026",
        "author": "PopBase"
      },
      {
        "text": "The Grammys afterparty tonight https://t.co/u61Ij2ZxHu",
        "likes": 24946,
        "retweets": 2819,
        "replies": 121,
        "timestamp": "Mon Feb 02 03:39:50 +0000 2026",
        "author": "Vision4theBlind"
      },
      {
        "text": "NEW: While other singers drop F bombs and virtue signal about ICE, Jelly Roll praises Jesus Christ at the Grammys.\n\n“I know they're gonna try to kick me off here, so just let me try to get this out.”\n\n“First of all, Jesus, I hear you and I'm listening, Lord. I am listening.”\n\n“I want to tell y'all right now, Jesus is for everybody. Jesus is not owned by one political party. Jesus is not owned by no music label. Jesus is Jesus and anybody, everybody can have a relationship with him…”",
        "likes": 56953,
        "retweets": 7617,
        "replies": 882,
        "timestamp": "Mon Feb 02 04:23:42 +0000 2026",
        "author": "CollinRugg"
      },
      {
        "text": "Bad Bunny teared up after winning the #GRAMMY for 'Album of the Year'\n\n'DeBÍ TiRAR MáS FOToS' makes history as the first all-Spanish language 'Album of the Year' winner in #GRAMMYs history. https://t.co/5NskHoTz15",
        "likes": 36245,
        "retweets": 3869,
        "replies": 169,
        "timestamp": "Mon Feb 02 04:40:14 +0000 2026",
        "author": "Kurrco"
      },
      {
        "text": "Im in tears. Jelly Roll goes on stage at the Grammys to praise Jesus Christ. Unlike EVERYONE else who praised Illegal Aliens taking over America \n\nJesus Christ is KING\n\nAbsolute CHILLS https://t.co/BOGkYMuJCb",
        "likes": 4789,
        "retweets": 732,
        "replies": 159,
        "timestamp": "Mon Feb 02 05:07:46 +0000 2026",
        "author": "MAGAVoice"
      },
      {
        "text": "Please take 60 seconds of your evening to watch this. \n\nJelly Roll SHOCKS the entire Grammys audience by giving praise to Jesus Christ. \n\nThe entire night consisted of “F*ck ICE” and anti-Trump comments up until this point. He shut that down. \n\nBeautiful moment. God bless him. 🙏🏻 https://t.co/H7SR7dgVwz",
        "likes": 13147,
        "retweets": 1376,
        "replies": 158,
        "timestamp": "Mon Feb 02 04:16:03 +0000 2026",
        "author": "jackunheard"
      },
      {
        "text": "While the rest of Hollywood is giving speeches defending illegal aliens, Jelly Roll used his time on stage at the Grammys to praise Jesus Christ.\n\nListen to this.\n\nCHILLS ✝️🙏🏻\n\n https://t.co/NwWvWdhJge",
        "likes": 35189,
        "retweets": 4760,
        "replies": 694,
        "timestamp": "Mon Feb 02 04:10:54 +0000 2026",
        "author": "bennyjohnson"
      },
      {
        "text": "Bad Bunny with the three #GRAMMYs he won today, including \"Album of the Year\". https://t.co/okhSge7E5i",
        "likes": 38639,
        "retweets": 4745,
        "replies": 60,
        "timestamp": "Mon Feb 02 06:10:46 +0000 2026",
        "author": "AccessBadBunny"
      },
      {
        "text": "Donald Trump slams the #GRAMMYs and threatens to sue Trevor Noah over Epstein Island remark:\n\n“It looks like I’ll be sending my lawyers to sue this poor, pathetic, talentless, dope of an M.C., and suing him for plenty$ […] Get ready Noah, I’m going to have some fun with you!” https://t.co/GFzKTyHTzg",
        "likes": 53234,
        "retweets": 2767,
        "replies": 1696,
        "timestamp": "Mon Feb 02 06:22:47 +0000 2026",
        "author": "PopBase"
      },
      {
        "text": "I’m so incredibly proud of you, ROSÉ.\ngetting nominated and performing at the Grammys is such a huge milestone, and seeing you stand on that stage felt unreal. All the hard work, dedication, and love you put into your music truly shines through. YOU DID AMAZING and this moment is so well deserved 🤍",
        "likes": 15324,
        "retweets": 5058,
        "replies": 119,
        "timestamp": "Mon Feb 02 04:23:44 +0000 2026",
        "author": "roseannepics"
      },
      {
        "text": "#GRAMMYs Record of the Year Winner: luther - Kendrick Lamar &amp; SZA https://t.co/ri7HtcsKdx",
        "likes": 23885,
        "retweets": 4270,
        "replies": 499,
        "timestamp": "Mon Feb 02 04:16:06 +0000 2026",
        "author": "chartdata"
      },
      {
        "text": "Miley Cyrus &amp; Bad Bunny together at the #Grammys  🥹🫶🏻 https://t.co/dIaGZFmee4",
        "likes": 22170,
        "retweets": 2325,
        "replies": 43,
        "timestamp": "Mon Feb 02 03:20:41 +0000 2026",
        "author": "MileyNation13"
      },
      {
        "text": "My favorite duo: Big Bad #Rosé and @BrunoMars! \n\n📍 2026 #GRAMMYs https://t.co/fSc4N7INHR",
        "likes": 13814,
        "retweets": 3687,
        "replies": 110,
        "timestamp": "Mon Feb 02 04:31:32 +0000 2026",
        "author": "MTV"
      },
      {
        "text": "🚨BREAKING: Hailey Bieber’s old tweet from 2012 is going viral after her Grammys appearance with an “ICE OUT” pin. https://t.co/fBf8F2fn3D",
        "likes": 10903,
        "retweets": 1300,
        "replies": 191,
        "timestamp": "Mon Feb 02 04:40:16 +0000 2026",
        "author": "ImMeme0"
      },
      {
        "text": "President Trump threatens to sue Trevor Noah for falsely claiming he went to Epstein Island at the Grammys https://t.co/wqdq8yITvg",
        "likes": 13584,
        "retweets": 2455,
        "replies": 692,
        "timestamp": "Mon Feb 02 06:46:44 +0000 2026",
        "author": "bennyjohnson"
      },
      {
        "text": "So we actually DO belong together 💍 @Harry_Styles\n\n📍 2026 #GRAMMYs https://t.co/w7LZWAjk4O",
        "likes": 7777,
        "retweets": 948,
        "replies": 37,
        "timestamp": "Mon Feb 02 04:55:06 +0000 2026",
        "author": "MTV"
      },
      {
        "text": "Lady Gaga was spotted wearing an “ICE OUT” pin in her bow at the #GRAMMYs https://t.co/zNp7TnSFzy",
        "likes": 19103,
        "retweets": 1718,
        "replies": 31,
        "timestamp": "Mon Feb 02 05:18:57 +0000 2026",
        "author": "gagadaily"
      },
      {
        "text": "Both of Tyler, The Creator's characters for 'CHORMAKOPIA' and 'DON'T TAP THE GLASS' died during his #GRAMMYs performance\n\nNew era on the way...? 👀 https://t.co/eMesei1V6J",
        "likes": 12583,
        "retweets": 712,
        "replies": 33,
        "timestamp": "Mon Feb 02 03:29:29 +0000 2026",
        "author": "Kurrco"
      },
      {
        "text": "Billie Eilish at the Grammys: \"Nobody is illegal on stolen land. We need to keep fighting and speaking up. Our voices do matter...f*ck ICE.\"\n\n https://t.co/90FQcO0Un2",
        "likes": 3307,
        "retweets": 325,
        "replies": 3798,
        "timestamp": "Mon Feb 02 03:22:53 +0000 2026",
        "author": "Breaking911"
      },
      {
        "text": "THE TWITTER GRAMMYS \nwho deserved AOTY???? https://t.co/TMEGTgtTW5",
        "likes": 5568,
        "retweets": 331,
        "replies": 76,
        "timestamp": "Mon Feb 02 04:26:17 +0000 2026",
        "author": "buffys"
      },
      {
        "text": "‘luther’ by Kendrick Lamar &amp; SZA wins the #GRAMMYs award for Record of the Year. https://t.co/YpfpoQhqFO",
        "likes": 25833,
        "retweets": 4588,
        "replies": 840,
        "timestamp": "Mon Feb 02 04:15:59 +0000 2026",
        "author": "PopBase"
      },
      {
        "text": "Billie Eilish says \"f*ck ICE!\" at the #Grammys while winning song of the year: \n\n\"No one is illegal on stolen land. It’s just really hard to know what to say and what to do right now, and I feel really hopeful in this room, and I feel like we just need to keep fighting and speaking up and protesting, and our voices really do matter, and the people matter. That’s all I’m going to say. Sorry. Thank you so much.\"\nhttps://t.co/xf46I69Y62",
        "likes": 8787,
        "retweets": 1275,
        "replies": 561,
        "timestamp": "Mon Feb 02 03:31:33 +0000 2026",
        "author": "Variety"
      },
      {
        "text": "cher at the grammys, icon https://t.co/I1vOB46kyM",
        "likes": 3374,
        "retweets": 344,
        "replies": 51,
        "timestamp": "Mon Feb 02 04:17:50 +0000 2026",
        "author": "PopCulture2000s"
      },
      {
        "text": "Tyler, The he Creator performance at the #GRAMMYs https://t.co/sdb8vcOLkO",
        "likes": 49059,
        "retweets": 8476,
        "replies": 162,
        "timestamp": "Mon Feb 02 03:31:37 +0000 2026",
        "author": "xerecadotyler"
      },
      {
        "text": "“Potato. If you had me saying ‘potato’ on Polymarket, you just made a ton of money so congratulations ‘Noah underscore 22,’ whoever that is.”\n\n— Trevor Noah during the #GRAMMYs. \n\n https://t.co/pmchxcOAXg",
        "likes": 8700,
        "retweets": 117,
        "replies": 141,
        "timestamp": "Mon Feb 02 05:05:24 +0000 2026",
        "author": "PopBase"
      },
      {
        "text": "Bad Bunny cries after winning Album of the Year at the GRAMMYs  https://t.co/11YrqclQsD",
        "likes": 49742,
        "retweets": 3063,
        "replies": 793,
        "timestamp": "Mon Feb 02 04:38:35 +0000 2026",
        "author": "FearedBuck"
      },
      {
        "text": "Jelly Roll was asked about politics after his #Grammys win and said \"people shouldn’t care to hear my opinion. I’m a dumb redneck.\"\n\n\"I hate to be  the artist that sounds aloof, but I just feel so disconnected from  what’s happening. I didn’t know politics were real until I was in my  mid-20s in jail. That’s how disconnected you are when you grow up in a  drug-addicted household.\"\n\nhttps://t.co/H6WLHcZ82X",
        "likes": 2929,
        "retweets": 130,
        "replies": 425,
        "timestamp": "Mon Feb 02 03:49:47 +0000 2026",
        "author": "Variety"
      },
      {
        "text": "hell yes to Billie Eilish's Grammys speech: \"No one is illegal on stolen land.\"\n\n\"It's really hard to know what to say and what to do right now, and I feel really hopeful in this room and I feel like we need to keep fighting and speaking up and protesting. Our voices really do matter, and people matter\"",
        "likes": 9571,
        "retweets": 1060,
        "replies": 326,
        "timestamp": "Mon Feb 02 03:14:56 +0000 2026",
        "author": "SpencerAlthouse"
      },
      {
        "text": "So-Called “Comedian” Trevor Noah mocks @NickiMinaj for standing up for persecuted Christians in Nigeria and supporting Trump Accounts at the Grammys.\n\n https://t.co/xDEMEGtFWT",
        "likes": 2986,
        "retweets": 369,
        "replies": 559,
        "timestamp": "Mon Feb 02 04:08:27 +0000 2026",
        "author": "bennyjohnson"
      },
      {
        "text": "Billie Eilish says \"f*ck ice\" during her #Grammys acceptance speech: \"Nobody is illegal on stolen land. We need to keep fighting and speaking up. Our voices do matter.\" https://t.co/Sz1um3afYJ",
        "likes": 26662,
        "retweets": 5216,
        "replies": 2075,
        "timestamp": "Mon Feb 02 03:15:33 +0000 2026",
        "author": "Variety"
      },
      {
        "text": "TYLER, THE CREATOR: ARTISTA! #GRAMMYs https://t.co/7UCRtGel29",
        "likes": 4063,
        "retweets": 689,
        "replies": 21,
        "timestamp": "Mon Feb 02 03:20:55 +0000 2026",
        "author": "tracklist"
      },
      {
        "text": "Nicki Minaj addresses the jabs thrown at her at the GRAMMYs.\n\n“As they do their ritual tonight, God almighty will reveal himself to them. The ritual will backfire on them. God will not be mocked. Blessed is the MIGHTY NAME OF JESUS CHRIST. Every tongue that rises up against me in judgement shall be condemned & put to shame. Watch 🪄✨”",
        "likes": 10726,
        "retweets": 727,
        "replies": 461,
        "timestamp": "Mon Feb 02 04:58:46 +0000 2026",
        "author": "FearedBuck"
      },
      {
        "text": "KENDRICK LAMAR &amp; SZA. \"LUTHER.\"\n\nRECORD OF THE YEAR #GRAMMYs WINNERS.\nRECORD OF THE YEAR #GRAMMYs WINNERS.\nRECORD OF THE YEAR #GRAMMYs WINNERS.\nRECORD OF THE YEAR #GRAMMYs WINNERS.\nRECORD OF THE YEAR #GRAMMYs WINNERS.\nRECORD OF THE YEAR #GRAMMYs WINNERS. https://t.co/TUiWyFZcCr",
        "likes": 2931,
        "retweets": 440,
        "replies": 23,
        "timestamp": "Mon Feb 02 04:20:20 +0000 2026",
        "author": "RollingStone"
      },
      {
        "text": "Just ran into the birthday boy backstage!! 🎉 \n\n📍 @Harry_Styles at the 2026 #GRAMMYs https://t.co/z3MsL1Oozy",
        "likes": 25404,
        "retweets": 3930,
        "replies": 358,
        "timestamp": "Mon Feb 02 04:01:35 +0000 2026",
        "author": "MTV"
      },
      {
        "text": "Bad Bunny with his Album of the Year #GRAMMYs award. https://t.co/SFEJznJlPv",
        "likes": 30161,
        "retweets": 5303,
        "replies": 402,
        "timestamp": "Mon Feb 02 04:35:38 +0000 2026",
        "author": "PopBase"
      },
      {
        "text": "I loveeee how hyped up the entire audience got when Lauryn Hill started singing Killing Me Softly at the Grammys. so perfect https://t.co/nytDnqlj1j",
        "likes": 15870,
        "retweets": 1915,
        "replies": 27,
        "timestamp": "Mon Feb 02 04:02:48 +0000 2026",
        "author": "SpencerAlthouse"
      },
      {
        "text": "Lady Gaga in the #GRAMMYs press room with her two awards that she won tonight. https://t.co/Fmub6GkyAU",
        "likes": 8636,
        "retweets": 1369,
        "replies": 32,
        "timestamp": "Mon Feb 02 06:06:15 +0000 2026",
        "author": "ladygaganownet"
      },
      {
        "text": "Doechii with her beautiful mom and sisters at the #GRAMMYs. https://t.co/ZMg4ybIha4",
        "likes": 16099,
        "retweets": 1108,
        "replies": 46,
        "timestamp": "Mon Feb 02 05:00:16 +0000 2026",
        "author": "doechiiupdates"
      },
      {
        "text": "🚨 Trump on the Grammys and Epstein Files 🚨 https://t.co/hnmJPPbovu",
        "likes": 8419,
        "retweets": 1212,
        "replies": 279,
        "timestamp": "Mon Feb 02 05:46:39 +0000 2026",
        "author": "ginamilan_"
      },
      {
        "text": "Lady Gaga and Chappell Roan #GRAMMYs https://t.co/phgIE4j804",
        "likes": 7665,
        "retweets": 952,
        "replies": 28,
        "timestamp": "Mon Feb 02 05:12:27 +0000 2026",
        "author": "gagadaily"
      },
      {
        "text": "🚨 A  MUST  WATCH  🏆 \n\nGod Bless JELLY ROLL  at the Grammys https://t.co/upoa0V6Dla",
        "likes": 5026,
        "retweets": 907,
        "replies": 157,
        "timestamp": "Mon Feb 02 05:18:06 +0000 2026",
        "author": "atensnut"
      },
      {
        "text": "Lady Gaga was the prize student of Marina Abramović, a ‘Spirit Cooker’ and Satanist. \n\nTonight, Lady Gaga sang about the ‘Devil’ during her Grammys performance. https://t.co/wcodGVTh9D",
        "likes": 2004,
        "retweets": 641,
        "replies": 161,
        "timestamp": "Mon Feb 02 04:18:43 +0000 2026",
        "author": "liz_churchill10"
      },
      {
        "text": "Bad Bunny gets emotional after winning Album of the Year at the #GRAMMYs. https://t.co/geLCUaJfHl",
        "likes": 61661,
        "retweets": 5563,
        "replies": 421,
        "timestamp": "Mon Feb 02 04:37:59 +0000 2026",
        "author": "PopBase"
      },
      {
        "text": "Bad Bunny crying after winning Album of the Year at the #GRAMMYs https://t.co/ZST8ouhrNf",
        "likes": 10007,
        "retweets": 856,
        "replies": 88,
        "timestamp": "Mon Feb 02 04:43:06 +0000 2026",
        "author": "vidsthatgohard"
      },
      {
        "text": "Post Malone honors Ozzy Osbourne with a heartfelt cover of \"War Pigs\" at the #Grammys, as Sharon, Kelly, and Jack watch in tears. https://t.co/GThZoiVJY2",
        "likes": 4094,
        "retweets": 448,
        "replies": 48,
        "timestamp": "Mon Feb 02 03:50:33 +0000 2026",
        "author": "Variety"
      },
      {
        "text": "Jelly Roll praises Jesus in Grammys acceptance speech. ✝️🙏\n\n“I know they’re going to try kick me off here so just let me try to get this out. First of all Jesus, I hear you and I’m listening Lord.”\n\n https://t.co/JxYIn7sVLh",
        "likes": 5215,
        "retweets": 402,
        "replies": 67,
        "timestamp": "Mon Feb 02 03:50:32 +0000 2026",
        "author": "OliLondonTV"
      },
      {
        "text": "Everyone say 'HAPPY BIRTHDAY @HARRY_STYLES' !!!!!!!\n\n📍 2026 #GRAMMYs https://t.co/uGEGEVk49E",
        "likes": 4751,
        "retweets": 723,
        "replies": 30,
        "timestamp": "Mon Feb 02 04:29:02 +0000 2026",
        "author": "MTV"
      },
      {
        "text": "Lady Gaga shares why she had such a tearful reaction to Bad Bunny’s historic Album of the Year win at the #GRAMMYs. https://t.co/wFeJTBSGRC",
        "likes": 11799,
        "retweets": 1241,
        "replies": 52,
        "timestamp": "Mon Feb 02 06:56:58 +0000 2026",
        "author": "etnow"
      },
      {
        "text": "Billie Eilish at the Grammys says, “Nobody is illegal on stolen land” and “F*** ICE.”\n\nSo stunning. So brave. So predictable.\n\nShe hates America.\n\nhttps://t.co/xCAGzlryxV",
        "likes": 2403,
        "retweets": 265,
        "replies": 1356,
        "timestamp": "Mon Feb 02 03:20:52 +0000 2026",
        "author": "Bubblebathgirl"
      },
      {
        "text": "Sabrina Carpenter and Bad Bunny at the #Grammys https://t.co/dFGvtomasX",
        "likes": 7832,
        "retweets": 514,
        "replies": 48,
        "timestamp": "Mon Feb 02 04:26:44 +0000 2026",
        "author": "Variety"
      },
      {
        "text": "Where do I apply to be part of this #GRAMMYs friend group?! 📝 \n\n🌟 #AddisonRae \n🌟 @laufey\n🌟 #ROSE https://t.co/hL6yUm0uRy",
        "likes": 3503,
        "retweets": 888,
        "replies": 30,
        "timestamp": "Mon Feb 02 03:23:14 +0000 2026",
        "author": "MTV"
      },
      {
        "text": "Harry backstage at the 2026 #GRAMMYs in Los Angeles, California - February 1 https://t.co/KirxgmfcYi",
        "likes": 7481,
        "retweets": 786,
        "replies": 54,
        "timestamp": "Mon Feb 02 04:53:09 +0000 2026",
        "author": "hsdaily"
      },
      {
        "text": "Bad Bunny's speech after winning his #GRAMMYs  in the \"Album Of The Year\" category with \"DeBÍ TiRAR MáS FOToS\". 🇵🇷 https://t.co/KxJrCWIGDe",
        "likes": 19687,
        "retweets": 4301,
        "replies": 66,
        "timestamp": "Mon Feb 02 04:42:58 +0000 2026",
        "author": "AccessBadBunny"
      },
      {
        "text": "CLIPSE\nPHARRELL\n\nSO FAR AHEAD\n\nLIVE AT THE #GRAMMYs  https://t.co/s034UpwqpO",
        "likes": 4054,
        "retweets": 593,
        "replies": 56,
        "timestamp": "Mon Feb 02 04:32:05 +0000 2026",
        "author": "Kurrco"
      },
      {
        "text": "Sabrina Carpenter and Chappell Roan at the 2026 #GRAMMYs. https://t.co/FjPSk43RD2",
        "likes": 10172,
        "retweets": 744,
        "replies": 99,
        "timestamp": "Mon Feb 02 03:51:48 +0000 2026",
        "author": "PopCrave"
      },
      {
        "text": "Since it’s #GRAMMYs  Day remember this ICONIC moment when the kings @BTS_twt performed “Butter” and received the standing ovation of the artists!\nhttps://t.co/2UzOytDmaq",
        "likes": 10215,
        "retweets": 2668,
        "replies": 21,
        "timestamp": "Mon Feb 02 05:23:15 +0000 2026",
        "author": "btschartsdailyc"
      },
      {
        "text": "It might be Harry Styles's birthday but he gave us ALL a gift by presenting album of the year at the Grammys 🪩🎂😍 https://t.co/t4QuPUf7hH",
        "likes": 775,
        "retweets": 140,
        "replies": 6,
        "timestamp": "Mon Feb 02 04:41:36 +0000 2026",
        "author": "GMA"
      },
      {
        "text": "#HeatedRivalry stars Connor Storrie &amp; Francois Arnaud are hitting up the #Grammys after-parties together! https://t.co/wdzLEm085n\n\nPics: Backgrid https://t.co/DqZPtbP8ER",
        "likes": 4161,
        "retweets": 449,
        "replies": 77,
        "timestamp": "Mon Feb 02 06:48:26 +0000 2026",
        "author": "JustJared"
      },
      {
        "text": "Billie Eilish called out Trump and ICE at the Grammys tonight “We need to keep fighting and speaking up. Our voices do matter… F*ck ICE.” Love to see it. https://t.co/oiItLxtghB",
        "likes": 3553,
        "retweets": 418,
        "replies": 141,
        "timestamp": "Mon Feb 02 04:33:49 +0000 2026",
        "author": "harryjsisson"
      },
      {
        "text": "‘Bad Bunny’ claims criminal illegal aliens are Americans at the Grammys.\n\n https://t.co/mDkcjSi4Nx",
        "likes": 1023,
        "retweets": 144,
        "replies": 731,
        "timestamp": "Mon Feb 02 04:07:29 +0000 2026",
        "author": "bennyjohnson"
      },
      {
        "text": "Insane. Jelly Roll got kicked off stage at the Grammys for praising Jesus Christ. \n\nDozens of artists shouted “F*ck ICE and Donald Trump” nonstop all night with no interruptions. \n\nSpiritual war. \n https://t.co/QpmU5SILXT",
        "likes": 18645,
        "retweets": 1163,
        "replies": 224,
        "timestamp": "Mon Feb 02 04:23:51 +0000 2026",
        "author": "jackunheard"
      },
      {
        "text": "Donald Trump says the #Grammys were \"virtually unwatchable\" and host Trevor Noah is \"a total loser\" for joking about Trump on Epstein Island: \"It looks like I’ll be sending my lawyers to sue this poor, pathetic, talentless, dope of an M.C.\" \n\n\"Noah said, INCORRECTLY about me, that Donald Trump and Bill Clinton spent time on Epstein Island. WRONG!!! I can’t speak for Bill, but I have never been to Epstein Island, nor anywhere close, and until tonight’s false and defamatory, statement, have never been accused being there, not even by the Fake News Media. Noah, a total loser, better get his facts straight, and get them straight fast. It looks like I’ll be sending my lawyers to sue this poor, pathetic, talentless, dope of an M.C., and suing him for plenty. Ask Little George Slopadopolus, and others, how that all worked out. Also ask CBS! Get ready Noah, I’m going to have some fun with you!\"\n\nhttps://t.co/5vmSuoTK8d",
        "likes": 821,
        "retweets": 126,
        "replies": 200,
        "timestamp": "Mon Feb 02 06:19:04 +0000 2026",
        "author": "Variety"
      },
      {
        "text": "Tate McRae and Zara Larsson reunite at the 2026 #GRAMMYs.\n\nhttps://t.co/Rx241dWVBq",
        "likes": 4027,
        "retweets": 161,
        "replies": 45,
        "timestamp": "Mon Feb 02 04:09:08 +0000 2026",
        "author": "PopCrave"
      },
      {
        "text": "Full Lauryn Hill tribute performance to D'Angelo and Roberta Flack at the #Grammys https://t.co/QNL6KZlwS0",
        "likes": 11009,
        "retweets": 3133,
        "replies": 86,
        "timestamp": "Mon Feb 02 04:10:20 +0000 2026",
        "author": "big_business_"
      },
      {
        "text": "Lady Gaga and Tate McRae at the 2026 #GRAMMYs. https://t.co/9hYiTv9L8P",
        "likes": 15144,
        "retweets": 1019,
        "replies": 208,
        "timestamp": "Mon Feb 02 03:38:20 +0000 2026",
        "author": "PopCrave"
      },
      {
        "text": "YUNGBLUD and Billie Eilish stun together at the 2026 #GRAMMYs. https://t.co/WeumeiEdYH",
        "likes": 2652,
        "retweets": 190,
        "replies": 60,
        "timestamp": "Mon Feb 02 04:00:45 +0000 2026",
        "author": "PopCrave"
      },
      {
        "text": "“the Grammy goes to Luther Vandross.”\n\n— Cher announcing the winner of ‘Record of the Year’ at the #GRAMMYs. https://t.co/rSTjjDdNIb",
        "likes": 45575,
        "retweets": 2358,
        "replies": 356,
        "timestamp": "Mon Feb 02 04:24:42 +0000 2026",
        "author": "PopBase"
      },
      {
        "text": "BREAKING 🅱️\n\nA Hailey Bieber tweet from 2012 is going viral after she wore an “ICE OUT” pin to the Grammys. \n\n👀 https://t.co/HuD0E5w2ai",
        "likes": 5364,
        "retweets": 698,
        "replies": 85,
        "timestamp": "Mon Feb 02 04:23:09 +0000 2026",
        "author": "iAnonPatriot"
      },
      {
        "text": "🚨 HARRY BIRTHDAY BOY STYLES!!!!! #GRAMMYs https://t.co/604JQteqeD",
        "likes": 4292,
        "retweets": 579,
        "replies": 4,
        "timestamp": "Mon Feb 02 04:33:19 +0000 2026",
        "author": "iHeartRadio"
      },
      {
        "text": "Lola Young's reaction to winning her first ever #GRAMMYs Award. https://t.co/B7oLeZQ0Ym",
        "likes": 7642,
        "retweets": 496,
        "replies": 111,
        "timestamp": "Mon Feb 02 04:12:48 +0000 2026",
        "author": "PopBase"
      },
      {
        "text": "Harry Styles backstage at the 2026 #GRAMMYs.\n\n https://t.co/shWlh4AK7K",
        "likes": 9037,
        "retweets": 496,
        "replies": 78,
        "timestamp": "Mon Feb 02 04:06:48 +0000 2026",
        "author": "PopCrave"
      },
      {
        "text": "Bad Bunny joins João Gilberto as the ONLY Latin artists to win the “Album of the Year” category at the #GRAMMYs. 🇵🇷🇧🇷 https://t.co/98HCU2E4t8",
        "likes": 14187,
        "retweets": 1471,
        "replies": 26,
        "timestamp": "Mon Feb 02 04:39:20 +0000 2026",
        "author": "AccessBadBunny"
      },
      {
        "text": "Harry Styles presenting ‘Album of the Year’ at the #GRAMMYs. https://t.co/FTQFSmscpL",
        "likes": 14905,
        "retweets": 1389,
        "replies": 168,
        "timestamp": "Mon Feb 02 04:32:33 +0000 2026",
        "author": "PopBase"
      },
      {
        "text": "Bad Bunny gets emotional after winning Album of the Year #Grammys https://t.co/Czbk3EKv9S",
        "likes": 14748,
        "retweets": 2016,
        "replies": 56,
        "timestamp": "Mon Feb 02 04:36:42 +0000 2026",
        "author": "DEADLINE"
      },
      {
        "text": "For the second consecutive year, the #GRAMMYs 'Album of the Year' winner was a first time recipient in the category:\n\nBeyoncé and Bad Bunny https://t.co/k3LMW6fNFo",
        "likes": 16567,
        "retweets": 1158,
        "replies": 76,
        "timestamp": "Mon Feb 02 04:45:00 +0000 2026",
        "author": "chartdata"
      },
      {
        "text": "TYLER, THE CREATOR\nSUGAR ON MY TONGUE\n\nLIVE AT THE #GRAMMYs \nhttps://t.co/hQpR6i8EK9",
        "likes": 9086,
        "retweets": 841,
        "replies": 113,
        "timestamp": "Mon Feb 02 03:21:34 +0000 2026",
        "author": "Kurrco"
      }
    ],
    "keywords": [
      [
        "grammys",
        84
      ],
      [
        "year",
        26
      ],
      [
        "bad",
        16
      ],
      [
        "bunny",
        15
      ],
      [
        "jesus",
        15
      ],
      [
        "album",
        13
      ],
      [
        "noah",
        11
      ],
      [
        "trump",
        10
      ],
      [
        "ice",
        10
      ],
      [
        "2026",
        10
      ]
    ],
    "hashtags": [
      [
        "#grammys",
        56
      ],
      [
        "#grammy",
        1
      ],
      [
        "#rosé",
        1
      ],
      [
        "#addisonrae",
        1
      ],
      [
        "#rose",
        1
      ],
      [
        "#heatedrivalry",
        1
      ]
    ],
    "sentiment": {
      "average": -0.0,
      "positive": 21,
      "neutral": 41,
      "negative": 17,
      "total": 79
    }
  },
  {
    "topic": "Good Monday",
    "score": 8.2,
    "source": "twitter",
    "discovered_at": "2026-02-02T11:22:59.969244+00:00",
    "region": "twitter_us",
    "niche": "General",
    "tweets": [
      {
        "text": "",
        "likes": 0,
        "retweets": 0,
        "replies": 0,
        "timestamp": "",
        "author": ""
      }
    ],
    "keywords": [],
    "hashtags": [],
    "sentiment": {
      "average": 0.0,
      "positive": 0,
      "neutral": 1,
      "negative": 0,
      "total": 1
    }
  }
]